LICENCE.md
MANIFEST.in
README.rst
setup.cfg
setup.py
jicbioimage/__init__.py
jicbioimage.transform.egg-info/PKG-INFO
jicbioimage.transform.egg-info/SOURCES.txt
jicbioimage.transform.egg-info/dependency_links.txt
jicbioimage.transform.egg-info/pbr.json
jicbioimage.transform.egg-info/requires.txt
jicbioimage.transform.egg-info/top_level.txt
jicbioimage/transform/__init__.py